openstudio/__init__.py
openstudio/_openstudioairflow.pyd
openstudio/_openstudioalfalfa.pyd
openstudio/_openstudioenergyplus.pyd
openstudio/_openstudioepjson.pyd
openstudio/_openstudiogbxml.pyd
openstudio/_openstudiogltf.pyd
openstudio/_openstudioisomodel.pyd
openstudio/_openstudiomeasure.pyd
openstudio/_openstudiomodel.pyd
openstudio/_openstudiomodelairflow.pyd
openstudio/_openstudiomodelavailabilitymanager.pyd
openstudio/_openstudiomodelcore.pyd
openstudio/_openstudiomodelgenerators.pyd
openstudio/_openstudiomodelgeometry.pyd
openstudio/_openstudiomodelhvac.pyd
openstudio/_openstudiomodelica.pyd
openstudio/_openstudiomodelplantequipmentoperationscheme.pyd
openstudio/_openstudiomodelrefrigeration.pyd
openstudio/_openstudiomodelresources.pyd
openstudio/_openstudiomodelsimulation.pyd
openstudio/_openstudiomodelstraightcomponent.pyd
openstudio/_openstudiomodelzonehvac.pyd
openstudio/_openstudioosversion.pyd
openstudio/_openstudioradiance.pyd
openstudio/_openstudiosdd.pyd
openstudio/_openstudioutilities.pyd
openstudio/_openstudioutilitiesbcl.pyd
openstudio/_openstudioutilitiescore.pyd
openstudio/_openstudioutilitiesdata.pyd
openstudio/_openstudioutilitiesfiletypes.pyd
openstudio/_openstudioutilitiesgeometry.pyd
openstudio/_openstudioutilitiesidd.pyd
openstudio/_openstudioutilitiesidf.pyd
openstudio/_openstudioutilitiesplot.pyd
openstudio/_openstudioutilitiessql.pyd
openstudio/_openstudioutilitiestime.pyd
openstudio/_openstudioutilitiesunits.pyd
openstudio/_openstudioutilitiesxml.pyd
openstudio/openstudioairflow.py
openstudio/openstudioalfalfa.py
openstudio/openstudioenergyplus.py
openstudio/openstudioepjson.py
openstudio/openstudiogbxml.py
openstudio/openstudiogltf.py
openstudio/openstudioisomodel.py
openstudio/openstudiolib.dll
openstudio/openstudiomeasure.py
openstudio/openstudiomodel.py
openstudio/openstudiomodelairflow.py
openstudio/openstudiomodelavailabilitymanager.py
openstudio/openstudiomodelcore.py
openstudio/openstudiomodelgenerators.py
openstudio-3.11.0.dist-info/METADATA
openstudio-3.11.0.dist-info/WHEEL
openstudio-3.11.0.dist-info/top_level.txt
openstudio-3.11.0.dist-info/RECORD
