Metadata-Version: 2.1
Name: openstudio
Version: 3.11.0
Summary: OpenStudio python bindings.
Home-page: https://github.com/NREL/OpenStudio
Author: Alliance for Energy Innovation, LLC, and other contributors
Author-email: openstudio@nrel.gov
Maintainer: Julien Marrec
Maintainer-email: contact@effibem.com
License: BSD3
Project-URL: Bug Tracker, https://github.com/NREL/OpenStudio/issues
Project-URL: Documentation, https://openstudio.net/
Project-URL: Source Code, https://github.com/NREL/OpenStudio
Keywords: openstudio py3 setuptools development
Platform: any
Classifier: Development Status :: 4 - Beta
Classifier: Environment :: Console
Classifier: Intended Audience :: Science/Research
Classifier: Topic :: Scientific/Engineering
Classifier: License :: OSI Approved :: BSD License
Classifier: Programming Language :: Python
Classifier: Programming Language :: Python :: 3
Classifier: Programming Language :: Python :: 3.7
Classifier: Programming Language :: Python :: 3.8
Classifier: Programming Language :: Python :: 3.9
Requires-Python: >=3.7.1
